Metadata-Version: 1.0
Name: Toxa
Version: 0.0.5
Summary: 
